ipfs_kit/__init__.py
ipfs_kit/install_ipfs.py
ipfs_kit/ipfs.py
ipfs_kit/ipfs_cluster_ctl.py
ipfs_kit/ipfs_cluster_follow.py
ipfs_kit/ipfs_cluster_service.py
ipfs_kit/ipfs_kit.py
ipfs_kit/ipget.py
ipfs_kit/s3_kit.py
ipfs_kit/test_fio.py
ipfs_kit-0.0.4.dist-info/LICENSE
ipfs_kit-0.0.4.dist-info/METADATA
ipfs_kit-0.0.4.dist-info/WHEEL
ipfs_kit-0.0.4.dist-info/top_level.txt
ipfs_kit-0.0.4.dist-info/RECORD
